AUTHORS
LICENSE
MANIFEST.in
README.md
setup.py
pyre/__init__.py
pyre/pyre.py
pyre/pyre_event.py
pyre/pyre_group.py
pyre/pyre_node.py
pyre/pyre_peer.py
pyre/zactor.py
pyre/zbeacon.py
pyre/zhelper.py
pyre/zre_msg.py
pyre/zsocket.py
zeromq_pyre.egg-info/PKG-INFO
zeromq_pyre.egg-info/SOURCES.txt
zeromq_pyre.egg-info/dependency_links.txt
zeromq_pyre.egg-info/requires.txt
zeromq_pyre.egg-info/top_level.txt