Metadata-Version: 2.1
Name: zeromq-pyre
Version: 0.3.3
Summary: Python ZRE implementation
Home-page: http://www.github.com/zeromq/pyre/
Author: Arnaud Loonstra
Author-email: arnaud@sphaero.org
License: UNKNOWN
Platform: UNKNOWN
Requires: pyzmq
Requires: ipaddress
License-File: LICENSE
License-File: AUTHORS
